karborclient/__init__.py
karborclient/client.py
karborclient/i18n.py
karborclient/shell.py
karborclient/version.py
karborclient/common/__init__.py
karborclient/common/base.py
karborclient/common/http.py
karborclient/common/utils.py
karborclient/openstack/__init__.py
karborclient/openstack/common/__init__.py
karborclient/openstack/common/apiclient/__init__.py
karborclient/openstack/common/apiclient/auth.py
karborclient/openstack/common/apiclient/base.py
karborclient/openstack/common/apiclient/client.py
karborclient/openstack/common/apiclient/exceptions.py
karborclient/openstack/common/apiclient/fake_client.py
karborclient/tests/__init__.py
karborclient/tests/unit/__init__.py
karborclient/tests/unit/base.py
karborclient/tests/unit/fakes.py
karborclient/tests/unit/test_http.py
karborclient/tests/unit/test_karborclient.py
karborclient/tests/unit/test_shell.py
karborclient/tests/unit/v1/__init__.py
karborclient/tests/unit/v1/fakes.py
karborclient/tests/unit/v1/test_checkpoints.py
karborclient/tests/unit/v1/test_plans.py
karborclient/tests/unit/v1/test_protectables.py
karborclient/tests/unit/v1/test_providers.py
karborclient/tests/unit/v1/test_restores.py
karborclient/tests/unit/v1/test_scheduled_operations.py
karborclient/tests/unit/v1/test_triggers.py
karborclient/v1/__init__.py
karborclient/v1/checkpoints.py
karborclient/v1/client.py
karborclient/v1/plans.py
karborclient/v1/protectables.py
karborclient/v1/providers.py
karborclient/v1/restores.py
karborclient/v1/scheduled_operations.py
karborclient/v1/shell.py
karborclient/v1/triggers.py
python_smaugclient-0.0.8.dist-info/DESCRIPTION.rst
python_smaugclient-0.0.8.dist-info/METADATA
python_smaugclient-0.0.8.dist-info/RECORD
python_smaugclient-0.0.8.dist-info/WHEEL
python_smaugclient-0.0.8.dist-info/entry_points.txt
python_smaugclient-0.0.8.dist-info/metadata.json
python_smaugclient-0.0.8.dist-info/pbr.json
python_smaugclient-0.0.8.dist-info/top_level.txt
