Metadata-Version: 2.0
Name: python-smaugclient
Version: 0.0.8
Summary: Python client library for Karbor API
Home-page: http://www.openstack.org/
Author: OpenStack
Author-email: openstack-dev@lists.openstack.org
License: UNKNOWN
Platform: UNKNOWN
Classifier: Environment :: OpenStack
Classifier: Intended Audience :: Information Technology
Classifier: Intended Audience :: System Administrators
Classifier: License :: OSI Approved :: Apache Software License
Classifier: Operating System :: POSIX :: Linux
Classifier: Programming Language :: Python
Classifier: Programming Language :: Python :: 2
Classifier: Programming Language :: Python :: 2.7
Classifier: Programming Language :: Python :: 3
Classifier: Programming Language :: Python :: 3.3
Classifier: Programming Language :: Python :: 3.4
Requires-Dist: Babel (>=2.3.4)
Requires-Dist: PrettyTable (<0.8,>=0.7)
Requires-Dist: oslo.i18n (>=2.1.0)
Requires-Dist: oslo.log (>=1.14.0)
Requires-Dist: oslo.utils (>=3.16.0)
Requires-Dist: pbr (>=1.6)
Requires-Dist: python-keystoneclient (>=1.7.0,!=1.8.0,!=2.1.0)
Requires-Dist: requests (>=2.10.0)
Requires-Dist: simplejson (>=2.2.0)
Requires-Dist: six (>=1.9.0)
